numpyro_oop/__init__.py
numpyro_oop/core.py
numpyro_oop-0.1.0.dist-info/LICENSE
numpyro_oop-0.1.0.dist-info/METADATA
numpyro_oop-0.1.0.dist-info/WHEEL
numpyro_oop-0.1.0.dist-info/top_level.txt
numpyro_oop-0.1.0.dist-info/RECORD
