Metadata-Version: 2.1
Name: numpyro-oop
Version: 0.1.0
Summary: A convenient object-oriented wrapper for working with numpyro models.
Author-email: Thomas Wallis <thomas.wallis@tu-darmstadt.de>
License: Copyright (c) 2024 Thomas Wallis
Keywords: numpyro,probabilistic programming,mcmc,bayesian inference
Classifier: Programming Language :: Python :: 3
Classifier: License :: OSI Approved :: MIT License
Classifier: Operating System :: OS Independent
Requires-Python: >=3.10
License-File: LICENSE
Requires-Dist: numpyro ~=0.15.0
Requires-Dist: pandas
Requires-Dist: arviz
Requires-Dist: graphviz
Provides-Extra: dev
Requires-Dist: pytest ; extra == 'dev'
Requires-Dist: black ; extra == 'dev'
Requires-Dist: jupyterlab ; extra == 'dev'
Requires-Dist: ipykernel ; extra == 'dev'
Requires-Dist: matplotlib ; extra == 'dev'
Requires-Dist: build ; extra == 'dev'
